task3/ram.sv
module ram #(
    parameter   ADDRESS_WIDTH = 9,
                DATA_WIDTH = 8
)(
    input logic clk,
    input logic wr_en,
    input logic rd_en,
    input logic [ADDRESS_WIDTH-1:0] wr_addr,
    input logic [ADDRESS_WIDTH-1:0] rd_addr,
    input logic [DATA_WIDTH-1:0] din,
    output logic [DATA_WIDTH-1:0] dout
);

logic [DATA_WIDTH-1:0] ram_array [2**ADDRESS_WIDTH-1:0];

always_ff @ (posedge clk) begin
    if (wr_en == 1'b1)
        ram_array[wr_addr] <= din;
    if (rd_en == 1'b1)
        // output is synchronous
        dout <= ram_array[rd_addr];
end
endmodule

task3/counter.sv
module counter #(
    parameter WIDTH = 8
)(
    //interface signals
    input logic clk,
    input logic rst,
    input logic en,
   // input logic [WIDTH-1:0] incr, // Ensuring this port is defined
    output logic [WIDTH-1:0] count
);

always_ff @ (posedge clk)
    if (rst) count <= {WIDTH{1'b0}};
    else count <= count + {WIDTH{1'b1}};

endmodule

task3/sigdelay.sv
module sigdelay #(
    parameter WIDTH = 8,
    parameter ADDRESS_WIDTH = 9,
    parameter DATA_WIDTH = 8
)(
    input logic clk,
    input logic rst,
    input logic en,
    input logic wr,
    input logic rd,
    input logic [ADDRESS_WIDTH-1:0] offset,
    input logic [DATA_WIDTH-1:0] mic_signal,
    output logic [DATA_WIDTH-1:0] delayed_signal
);

    // Counter signals
    logic [ADDRESS_WIDTH-1:0] wr_addr;

    // Instantiate the counter
    counter addrCounter(
        .clk(clk),
        .rst(rst),
        .en(en),
        .count(wr_addr)
    );

    logic [ADDRESS_WIDTH-1:0] rd_addr;
    assign rd_addr = wr_addr - offset;

    // Instantiate the dual-port RAM
    ram micram(
        .clk(clk),
        .wr_addr(wr_addr),
        .rd_addr(rd_addr),
        .din(mic_signal),
        .dout(delayed_signal),
        .wr_en(wr),
        .rd_en(rd)
    );


endmodule

task3/sigdelay.vcd
$version Generated by VerilatedVcd $end
$date Fri Oct 25 12:21:07 2024 $end
$timescale 1ps $end

 $scope module TOP $end
  $var wire  1 # clk $end
  $var wire  8 * delayed_signal [7:0] $end
  $var wire  1 % en $end
  $var wire  8 ) mic_signal [7:0] $end
  $var wire  9 ( offset [8:0] $end
  $var wire  1 ' rd $end
  $var wire  1 $ rst $end
  $var wire  1 & wr $end
  $scope module sigdelay $end
   $var wire 32 / ADDRESS_WIDTH [31:0] $end
   $var wire 32 . DATA_WIDTH [31:0] $end
   $var wire 32 . WIDTH [31:0] $end
   $var wire  1 # clk $end
   $var wire  8 * delayed_signal [7:0] $end
   $var wire  1 % en $end
   $var wire  8 ) mic_signal [7:0] $end
   $var wire  9 ( offset [8:0] $end
   $var wire  1 ' rd $end
   $var wire  9 , rd_addr [8:0] $end
   $var wire  1 $ rst $end
   $var wire  1 & wr $end
   $var wire  9 + wr_addr [8:0] $end
   $scope module addrCounter $end
    $var wire 32 . WIDTH [31:0] $end
    $var wire  1 # clk $end
    $var wire  8 - count [7:0] $end
    $var wire  1 % en $end
    $var wire  1 $ rst $end
   $upscope $end
   $scope module micram $end
    $var wire 32 / ADDRESS_WIDTH [31:0] $end
    $var wire 32 . DATA_WIDTH [31:0] $end
    $var wire  1 # clk $end
    $var wire  8 ) din [7:0] $end
    $var wire  8 * dout [7:0] $end
    $var wire  9 , rd_addr [8:0] $end
    $var wire  1 ' rd_en $end
    $var wire  9 + wr_addr [8:0] $end
    $var wire  1 & wr_en $end
   $upscope $end
  $upscope $end
 $upscope $end
$enddefinitions $end


#0
1#
0$
1%
1&
1'
b001000000 (
b00000000 )
b00000000 *
b000000000 +
b111000000 ,
b00000000 -
b00000000000000000000000000001000 .
b00000000000000000000000000001001 /
#1
0#
#2
1#
b000110011 (
b01001011 )
b011111111 +
b011001100 ,
b11111111 -
#3
0#
#4
1#
b01001001 )
b011111110 +
b011001011 ,
b11111110 -
#5
0#
#6
1#
b01010001 )
b011111101 +
b011001010 ,
b11111101 -
#7
0#
#8
1#
b01011000 )
b011111100 +
b011001001 ,
b11111100 -
#9
0#
#10
1#
b01100110 )
b011111011 +
b011001000 ,
b11111011 -
#11
0#
#12
1#
b01110000 )
b011111010 +
b011000111 ,
b11111010 -
#13
0#
#14
1#
b01110001 )
b011111001 +
b011000110 ,
b11111001 -
#15
0#
#16
1#
b01110100 )
b011111000 +
b011000101 ,
b11111000 -
#17
0#
#18
1#
b01111010 )
b011110111 +
b011000100 ,
b11110111 -
#19
0#
#20
1#
b011110110 +
b011000011 ,
b11110110 -
#21
0#
#22
1#
b01111101 )
b011110101 +
b011000010 ,
b11110101 -
#23
0#
#24
1#
b011110100 +
b011000001 ,
b11110100 -
#25
0#
#26
1#
b01111000 )
b011110011 +
b011000000 ,
b11110011 -
#27
0#
#28
1#
b01111010 )
b011110010 +
b010111111 ,
b11110010 -
#29
0#
#30
1#
b01110111 )
b011110001 +
b010111110 ,
b11110001 -
#31
0#
#32
1#
b011110000 +
b010111101 ,
b11110000 -
#33
0#
#34
1#
b011101111 +
b010111100 ,
b11101111 -
#35
0#
#36
1#
b01101101 )
b011101110 +
b010111011 ,
b11101110 -
#37
0#
#38
1#
b01100111 )
b011101101 +
b010111010 ,
b11101101 -
#39
0#
#40
1#
b01100001 )
b011101100 +
b010111001 ,
b11101100 -
#41
0#
#42
1#
b01011101 )
b011101011 +
b010111000 ,
b11101011 -
#43
0#
#44
1#
b01011100 )
b011101010 +
b010110111 ,
b11101010 -
#45
0#
#46
1#
b01011011 )
b011101001 +
b010110110 ,
b11101001 -
#47
0#
#48
1#
b01011010 )
b011101000 +
b010110101 ,
b11101000 -
#49
0#
#50
1#
b01011111 )
b011100111 +
b010110100 ,
b11100111 -
#51
0#
#52
1#
b01100011 )
b011100110 +
b010110011 ,
b11100110 -
#53
0#
#54
1#
b011100101 +
b010110010 ,
b11100101 -
#55
0#
#56
1#
b011100100 +
b010110001 ,
b11100100 -
#57
0#
#58
1#
b01100010 )
b011100011 +
b010110000 ,
b11100011 -
#59
0#
#60
1#
b01100100 )
b011100010 +
b010101111 ,
b11100010 -
#61
0#
#62
1#
b01101100 )
b011100001 +
b010101110 ,
b11100001 -
#63
0#
#64
1#
b01101110 )
b011100000 +
b010101101 ,
b11100000 -
#65
0#
#66
1#
b01101010 )
b011011111 +
b010101100 ,
b11011111 -
#67
0#
#68
1#
b01100100 )
b011011110 +
b010101011 ,
b11011110 -
#69
0#
#70
1#
b01100001 )
b011011101 +
b010101010 ,
b11011101 -
#71
0#
#72
1#
b01100000 )
b011011100 +
b010101001 ,
b11011100 -
#73
0#
#74
1#
b01011110 )
b011011011 +
b010101000 ,
b11011011 -
#75
0#
#76
1#
b01011001 )
b011011010 +
b010100111 ,
b11011010 -
#77
0#
#78
1#
b01011010 )
b011011001 +
b010100110 ,
b11011001 -
#79
0#
#80
1#
b01011011 )
b011011000 +
b010100101 ,
b11011000 -
#81
0#
#82
1#
b01011111 )
b011010111 +
b010100100 ,
b11010111 -
#83
0#
#84
1#
b01100110 )
b011010110 +
b010100011 ,
b11010110 -
#85
0#
#86
1#
b01101001 )
b011010101 +
b010100010 ,
b11010101 -
#87
0#
#88
1#
b01110100 )
b011010100 +
b010100001 ,
b11010100 -
#89
0#
#90
1#
b01110110 )
b011010011 +
b010100000 ,
b11010011 -
#91
0#
#92
1#
b01110111 )
b011010010 +
b010011111 ,
b11010010 -
#93
0#
#94
1#
b01111001 )
b011010001 +
b010011110 ,
b11010001 -
#95
0#
#96
1#
b01111000 )
b011010000 +
b010011101 ,
b11010000 -
#97
0#
#98
1#
b01110111 )
b011001111 +
b010011100 ,
b11001111 -
#99
0#
#100
1#
b01110101 )
b011001110 +
b010011011 ,
b11001110 -
#101
0#
#102
1#
b011001101 +
b010011010 ,
b11001101 -
#103
0#
#104
1#
b01110011 )
b011001100 +
b010011001 ,
b11001100 -
#105
0#
#106
1#
b011001011 +
b010011000 ,
b11001011 -
#107
0#
#108
1#
b01111000 )
b011001010 +
b010010111 ,
b11001010 -
#109
0#
#110
1#
b01111010 )
b011001001 +
b010010110 ,
b11001001 -
#111
0#
#112
1#
b01111101 )
b011001000 +
b010010101 ,
b11001000 -
#113
0#
#114
1#
b01111010 )
b011000111 +
b010010100 ,
b11000111 -
#115
0#
#116
1#
b01111011 )
b011000110 +
b010010011 ,
b11000110 -
#117
0#
#118
1#
b01111000 )
b011000101 +
b010010010 ,
b11000101 -
#119
0#
#120
1#
b01110110 )
b011000100 +
b010010001 ,
b11000100 -
#121
0#
#122
1#
b01110100 )
b011000011 +
b010010000 ,
b11000011 -
#123
0#
#124
1#
b01110001 )
b011000010 +
b010001111 ,
b11000010 -
#125
0#
#126
1#
b01101101 )
b011000001 +
b010001110 ,
b11000001 -
#127
0#
#128
1#
b01101001 )
b011000000 +
b010001101 ,
b11000000 -
#129
0#
#130
1#
b01101000 )
b010111111 +
b010001100 ,
b10111111 -
#131
0#
#132
1#
b01101011 )
b010111110 +
b010001011 ,
b10111110 -
#133
0#
#134
1#
b010111101 +
b010001010 ,
b10111101 -
#135
0#
#136
1#
b01101110 )
b010111100 +
b010001001 ,
b10111100 -
#137
0#
#138
1#
b01101100 )
b010111011 +
b010001000 ,
b10111011 -
#139
0#
#140
1#
b01100111 )
b010111010 +
b010000111 ,
b10111010 -
#141
0#
#142
1#
b01100010 )
b010111001 +
b010000110 ,
b10111001 -
#143
0#
#144
1#
b01100001 )
b010111000 +
b010000101 ,
b10111000 -
#145
0#
#146
1#
b01100010 )
b010110111 +
b010000100 ,
b10110111 -
#147
0#
#148
1#
b01100011 )
b010110110 +
b010000011 ,
b10110110 -
#149
0#
#150
1#
b01100000 )
b010110101 +
b010000010 ,
b10110101 -
#151
0#
#152
1#
b010110100 +
b010000001 ,
b10110100 -
#153
0#
#154
1#
b01100100 )
b010110011 +
b010000000 ,
b10110011 -
#155
0#
#156
1#
b01100110 )
b010110010 +
b001111111 ,
b10110010 -
#157
0#
#158
1#
b01101100 )
b010110001 +
b001111110 ,
b10110001 -
#159
0#
#160
1#
b01101101 )
b010110000 +
b001111101 ,
b10110000 -
#161
0#
#162
1#
b01101100 )
b010101111 +
b001111100 ,
b10101111 -
#163
0#
#164
1#
b01101111 )
b010101110 +
b001111011 ,
b10101110 -
#165
0#
#166
1#
b01110001 )
b010101101 +
b001111010 ,
b10101101 -
#167
0#
#168
1#
b010101100 +
b001111001 ,
b10101100 -
#169
0#
#170
1#
b01101100 )
b010101011 +
b001111000 ,
b10101011 -
#171
0#
#172
1#
b01100110 )
b010101010 +
b001110111 ,
b10101010 -
#173
0#
#174
1#
b01100101 )
b010101001 +
b001110110 ,
b10101001 -
#175
0#
#176
1#
b010101000 +
b001110101 ,
b10101000 -
#177
0#
#178
1#
b01100100 )
b010100111 +
b001110100 ,
b10100111 -
#179
0#
#180
1#
b01101010 )
b010100110 +
b001110011 ,
b10100110 -
#181
0#
#182
1#
b01100110 )
b010100101 +
b001110010 ,
b10100101 -
#183
0#
#184
1#
b01100111 )
b010100100 +
b001110001 ,
b10100100 -
#185
0#
#186
1#
b01101110 )
b010100011 +
b001110000 ,
b10100011 -
#187
0#
#188
1#
b01101100 )
b010100010 +
b001101111 ,
b10100010 -
#189
0#
#190
1#
b01101101 )
b010100001 +
b001101110 ,
b10100001 -
#191
0#
#192
1#
b01101011 )
b010100000 +
b001101101 ,
b10100000 -
#193
0#
#194
1#
b01100100 )
b010011111 +
b001101100 ,
b10011111 -
#195
0#
#196
1#
b010011110 +
b001101011 ,
b10011110 -
#197
0#
#198
1#
b01100011 )
b010011101 +
b001101010 ,
b10011101 -
#199
0#
#200
1#
b01100100 )
b010011100 +
b001101001 ,
b10011100 -
#201
0#
#202
1#
b01101011 )
b010011011 +
b001101000 ,
b10011011 -
#203
0#
#204
1#
b01101001 )
b010011010 +
b001100111 ,
b10011010 -
#205
0#
#206
1#
b01101101 )
b010011001 +
b001100110 ,
b10011001 -
#207
0#
#208
1#
b01101111 )
b010011000 +
b001100101 ,
b10011000 -
#209
0#
#210
1#
b01101101 )
b010010111 +
b001100100 ,
b10010111 -
#211
0#
#212
1#
b01101100 )
b010010110 +
b001100011 ,
b10010110 -
#213
0#
#214
1#
b01101000 )
b010010101 +
b001100010 ,
b10010101 -
#215
0#
#216
1#
b01101010 )
b010010100 +
b001100001 ,
b10010100 -
#217
0#
#218
1#
b01101110 )
b010010011 +
b001100000 ,
b10010011 -
#219
0#
#220
1#
b010010010 +
b001011111 ,
b10010010 -
#221
0#
#222
1#
b01101101 )
b010010001 +
b001011110 ,
b10010001 -
#223
0#
#224
1#
b01101110 )
b010010000 +
b001011101 ,
b10010000 -
#225
0#
#226
1#
b01101011 )
b010001111 +
b001011100 ,
b10001111 -
#227
0#
#228
1#
b01101101 )
b010001110 +
b001011011 ,
b10001110 -
#229
0#
#230
1#
b01101110 )
b010001101 +
b001011010 ,
b10001101 -
#231
0#
#232
1#
b01101011 )
b010001100 +
b001011001 ,
b10001100 -
#233
0#
#234
1#
b01101001 )
b010001011 +
b001011000 ,
b10001011 -
#235
0#
#236
1#
b01100110 )
b010001010 +
b001010111 ,
b10001010 -
#237
0#
#238
1#
b01100011 )
b010001001 +
b001010110 ,
b10001001 -
#239
0#
#240
1#
b01100010 )
b010001000 +
b001010101 ,
b10001000 -
#241
0#
#242
1#
b01011111 )
b010000111 +
b001010100 ,
b10000111 -
#243
0#
#244
1#
b01011101 )
b010000110 +
b001010011 ,
b10000110 -
#245
0#
#246
1#
b01011010 )
b010000101 +
b001010010 ,
b10000101 -
#247
0#
#248
1#
b01011100 )
b010000100 +
b001010001 ,
b10000100 -
#249
0#
#250
1#
b01100011 )
b010000011 +
b001010000 ,
b10000011 -
#251
0#
#252
1#
b01100111 )
b010000010 +
b001001111 ,
b10000010 -
#253
0#
#254
1#
b01110000 )
b010000001 +
b001001110 ,
b10000001 -
#255
0#
#256
1#
b01110110 )
b010000000 +
b001001101 ,
b10000000 -
#257
0#
#258
1#
b001111111 +
b001001100 ,
b01111111 -
#259
0#
#260
1#
b01110111 )
b001111110 +
b001001011 ,
b01111110 -
#261
0#
#262
1#
b001111101 +
b001001010 ,
b01111101 -
#263
0#
#264
1#
b01111010 )
b001111100 +
b001001001 ,
b01111100 -
#265
0#
#266
1#
b01110101 )
b001111011 +
b001001000 ,
b01111011 -
#267
0#
#268
1#
b001111010 +
b001000111 ,
b01111010 -
#269
0#
#270
1#
b01110010 )
b001111001 +
b001000110 ,
b01111001 -
#271
0#
#272
1#
b001111000 +
b001000101 ,
b01111000 -
#273
0#
#274
1#
b01110000 )
b001110111 +
b001000100 ,
b01110111 -
#275
0#
#276
1#
b001110110 +
b001000011 ,
b01110110 -
#277
0#
#278
1#
b001110101 +
b001000010 ,
b01110101 -
#279
0#
#280
1#
b01110100 )
b001110100 +
b001000001 ,
b01110100 -
#281
0#
#282
1#
b01110010 )
b001110011 +
b001000000 ,
b01110011 -
#283
0#
#284
1#
b01101110 )
b001110010 +
b000111111 ,
b01110010 -
#285
0#
#286
1#
b01101001 )
b001110001 +
b000111110 ,
b01110001 -
#287
0#
#288
1#
b01101000 )
b001110000 +
b000111101 ,
b01110000 -
#289
0#
#290
1#
b01100111 )
b001101111 +
b000111100 ,
b01101111 -
#291
0#
#292
1#
b01101001 )
b001101110 +
b000111011 ,
b01101110 -
#293
0#
#294
1#
b01110000 )
b001101101 +
b000111010 ,
b01101101 -
#295
0#
#296
1#
b01110100 )
b001101100 +
b000111001 ,
b01101100 -
#297
0#
#298
1#
b01110111 )
b001101011 +
b000111000 ,
b01101011 -
#299
0#
#300
1#
b01111000 )
b001101010 +
b000110111 ,
b01101010 -
#301
0#
#302
1#
b01110111 )
b001101001 +
b000110110 ,
b01101001 -
#303
0#
#304
1#
b01110011 )
b001101000 +
b000110101 ,
b01101000 -
#305
0#
#306
1#
b01101101 )
b001100111 +
b000110100 ,
b01100111 -
#307
0#
#308
1#
b01100110 )
b001100110 +
b000110011 ,
b01100110 -
#309
0#
#310
1#
b01100010 )
b001100101 +
b000110010 ,
b01100101 -
#311
0#
#312
1#
b01011111 )
b001100100 +
b000110001 ,
b01100100 -
#313
0#
#314
1#
b01100000 )
b001100011 +
b000110000 ,
b01100011 -
#315
0#
#316
1#
b01100010 )
b001100010 +
b000101111 ,
b01100010 -
#317
0#
#318
1#
b01100001 )
b001100001 +
b000101110 ,
b01100001 -
#319
0#
#320
1#
b01100000 )
b001100000 +
b000101101 ,
b01100000 -
#321
0#
#322
1#
b001011111 +
b000101100 ,
b01011111 -
#323
0#
#324
1#
b01100011 )
b001011110 +
b000101011 ,
b01011110 -
#325
0#
#326
1#
b01101011 )
b001011101 +
b000101010 ,
b01011101 -
#327
0#
#328
1#
b01101100 )
b001011100 +
b000101001 ,
b01011100 -
#329
0#
#330
1#
b01101101 )
b001011011 +
b000101000 ,
b01011011 -
#331
0#
#332
1#
b01101001 )
b001011010 +
b000100111 ,
b01011010 -
#333
0#
#334
1#
b01101000 )
b001011001 +
b000100110 ,
b01011001 -
#335
0#
#336
1#
b01100011 )
b001011000 +
b000100101 ,
b01011000 -
#337
0#
#338
1#
b01100000 )
b001010111 +
b000100100 ,
b01010111 -
#339
0#
#340
1#
b01011100 )
b001010110 +
b000100011 ,
b01010110 -
#341
0#
#342
1#
b001010101 +
b000100010 ,
b01010101 -
#343
0#
#344
1#
b01011110 )
b001010100 +
b000100001 ,
b01010100 -
#345
0#
#346
1#
b01100000 )
b001010011 +
b000100000 ,
b01010011 -
#347
0#
#348
1#
b01101000 )
b001010010 +
b000011111 ,
b01010010 -
#349
0#
#350
1#
b01101001 )
b001010001 +
b000011110 ,
b01010001 -
#351
0#
#352
1#
b01101101 )
b001010000 +
b000011101 ,
b01010000 -
#353
0#
#354
1#
b01101100 )
b001001111 +
b000011100 ,
b01001111 -
#355
0#
#356
1#
b001001110 +
b000011011 ,
b01001110 -
#357
0#
#358
1#
b01101011 )
b001001101 +
b000011010 ,
b01001101 -
#359
0#
#360
1#
b01101001 )
b001001100 +
b000011001 ,
b01001100 -
#361
0#
#362
1#
b01100110 )
b001001011 +
b000011000 ,
b01001011 -
#363
0#
#364
1#
b01100011 )
b001001010 +
b000010111 ,
b01001010 -
#365
0#
#366
1#
b01011111 )
b001001001 +
b000010110 ,
b01001001 -
#367
0#
#368
1#
b01100001 )
b001001000 +
b000010101 ,
b01001000 -
#369
0#
#370
1#
b01101010 )
b001000111 +
b000010100 ,
b01000111 -
#371
0#
#372
1#
b01101111 )
b001000110 +
b000010011 ,
b01000110 -
#373
0#
#374
1#
b01110000 )
b001000101 +
b000010010 ,
b01000101 -
#375
0#
#376
1#
b001000100 +
b000010001 ,
b01000100 -
#377
0#
#378
1#
b01101101 )
b001000011 +
b000010000 ,
b01000011 -
#379
0#
#380
1#
b01101011 )
b001000010 +
b000001111 ,
b01000010 -
#381
0#
#382
1#
b01101000 )
b001000001 +
b000001110 ,
b01000001 -
#383
0#
#384
1#
b01100110 )
b001000000 +
b000001101 ,
b01000000 -
#385
0#
#386
1#
b01100101 )
b000111111 +
b000001100 ,
b00111111 -
#387
0#
#388
1#
b01011011 )
b000111110 +
b000001011 ,
b00111110 -
#389
0#
#390
1#
b000111101 +
b000001010 ,
b00111101 -
#391
0#
#392
1#
b01010101 )
b000111100 +
b000001001 ,
b00111100 -
#393
0#
#394
1#
b01010000 )
b000111011 +
b000001000 ,
b00111011 -
#395
0#
#396
1#
b01010010 )
b000111010 +
b000000111 ,
b00111010 -
#397
0#
#398
1#
b01010001 )
b000111001 +
b000000110 ,
b00111001 -
#399
0#
#400
1#
b01001101 )
b000111000 +
b000000101 ,
b00111000 -
#401
0#
#402
1#
b01010001 )
b000110111 +
b000000100 ,
b00110111 -
#403
0#
#404
1#
b000110110 +
b000000011 ,
b00110110 -
#405
0#
#406
1#
b01010101 )
b000110101 +
b000000010 ,
b00110101 -
#407
0#
#408
1#
b01010110 )
b000110100 +
b000000001 ,
b00110100 -
#409
0#
#410
1#
b01010010 )
b000110011 +
b000000000 ,
b00110011 -
#411
0#
#412
1#
b01010110 )
b000110010 +
b111111111 ,
b00110010 -
#413
0#
#414
1#
b01011110 )
b000110001 +
b111111110 ,
b00110001 -
#415
0#
#416
1#
b01100010 )
b000110000 +
b111111101 ,
b00110000 -
#417
0#
#418
1#
b01101110 )
b000101111 +
b111111100 ,
b00101111 -
#419
0#
#420
1#
b01111101 )
b000101110 +
b111111011 ,
b00101110 -
#421
0#
#422
1#
b10000011 )
b000101101 +
b111111010 ,
b00101101 -
#423
0#
#424
1#
b10001000 )
b000101100 +
b111111001 ,
b00101100 -
#425
0#
#426
1#
b10001010 )
b000101011 +
b111111000 ,
b00101011 -
#427
0#
#428
1#
b10001101 )
b000101010 +
b111110111 ,
b00101010 -
#429
0#
#430
1#
b10001100 )
b000101001 +
b111110110 ,
b00101001 -
#431
0#
#432
1#
b10000110 )
b000101000 +
b111110101 ,
b00101000 -
#433
0#
#434
1#
b10000011 )
b000100111 +
b111110100 ,
b00100111 -
#435
0#
#436
1#
b000100110 +
b111110011 ,
b00100110 -
#437
0#
#438
1#
b01111001 )
b000100101 +
b111110010 ,
b00100101 -
#439
0#
#440
1#
b01110010 )
b000100100 +
b111110001 ,
b00100100 -
#441
0#
#442
1#
b01101100 )
b000100011 +
b111110000 ,
b00100011 -
#443
0#
#444
1#
b01100111 )
b000100010 +
b111101111 ,
b00100010 -
#445
0#
#446
1#
b01100010 )
b000100001 +
b111101110 ,
b00100001 -
#447
0#
#448
1#
b01100001 )
b000100000 +
b111101101 ,
b00100000 -
#449
0#
#450
1#
b01100100 )
b000011111 +
b111101100 ,
b00011111 -
#451
0#
#452
1#
b01100101 )
b000011110 +
b111101011 ,
b00011110 -
#453
0#
#454
1#
b01100111 )
b000011101 +
b111101010 ,
b00011101 -
#455
0#
#456
1#
b01101010 )
b000011100 +
b111101001 ,
b00011100 -
#457
0#
#458
1#
b01101100 )
b000011011 +
b111101000 ,
b00011011 -
#459
0#
#460
1#
b01100111 )
b000011010 +
b111100111 ,
b00011010 -
#461
0#
#462
1#
b01100110 )
b000011001 +
b111100110 ,
b00011001 -
#463
0#
#464
1#
b01100100 )
b000011000 +
b111100101 ,
b00011000 -
#465
0#
#466
1#
b000010111 +
b111100100 ,
b00010111 -
#467
0#
#468
1#
b01100001 )
b000010110 +
b111100011 ,
b00010110 -
#469
0#
#470
1#
b01100100 )
b000010101 +
b111100010 ,
b00010101 -
#471
0#
#472
1#
b01100111 )
b000010100 +
b111100001 ,
b00010100 -
#473
0#
#474
1#
b01101010 )
b000010011 +
b111100000 ,
b00010011 -
#475
0#
#476
1#
b01101101 )
b000010010 +
b111011111 ,
b00010010 -
#477
0#
#478
1#
b01101111 )
b000010001 +
b111011110 ,
b00010001 -
#479
0#
#480
1#
b01101101 )
b000010000 +
b111011101 ,
b00010000 -
#481
0#
#482
1#
b000001111 +
b111011100 ,
b00001111 -
#483
0#
#484
1#
b01101111 )
b000001110 +
b111011011 ,
b00001110 -
#485
0#
#486
1#
b000001101 +
b111011010 ,
b00001101 -
#487
0#
#488
1#
b01101101 )
b000001100 +
b111011001 ,
b00001100 -
#489
0#
#490
1#
b01110100 )
b000001011 +
b111011000 ,
b00001011 -
#491
0#
#492
1#
b01110011 )
b000001010 +
b111010111 ,
b00001010 -
#493
0#
#494
1#
b01110000 )
b000001001 +
b111010110 ,
b00001001 -
#495
0#
#496
1#
b01101100 )
b000001000 +
b111010101 ,
b00001000 -
#497
0#
#498
1#
b01101011 )
b000000111 +
b111010100 ,
b00000111 -
#499
0#
#500
1#
b01101000 )
b000000110 +
b111010011 ,
b00000110 -
#501
0#
#502
1#
b01101001 )
b000000101 +
b111010010 ,
b00000101 -
#503
0#
#504
1#
b000000100 +
b111010001 ,
b00000100 -
#505
0#
#506
1#
b01101100 )
b000000011 +
b111010000 ,
b00000011 -
#507
0#
#508
1#
b01101011 )
b000000010 +
b111001111 ,
b00000010 -
#509
0#
#510
1#
b01101110 )
b000000001 +
b111001110 ,
b00000001 -
#511
0#
#512
1#
b01101011 )
b000000000 +
b111001101 ,
b00000000 -
#513
0#
#514
1#
b01101101 )
b011111111 +
b011001100 ,
b11111111 -
#515
0#
#516
1#
b01101000 )
b01110011 *
b011111110 +
b011001011 ,
b11111110 -
#517
0#
#518
1#
b01100111 )
b011111101 +
b011001010 ,
b11111101 -
#519
0#
#520
1#
b01011011 )
b01111000 *
b011111100 +
b011001001 ,
b11111100 -
#521
0#
#522
1#
b01010101 )
b01111010 *
b011111011 +
b011001000 ,
b11111011 -
#523
0#
#524
1#
b01001111 )
b01111101 *
b011111010 +
b011000111 ,
b11111010 -
#525
0#
#526
1#
b01001001 )
b01111010 *
b011111001 +
b011000110 ,
b11111001 -
#527
0#
#528
1#
b01000110 )
b01111011 *
b011111000 +
b011000101 ,
b11111000 -
#529
0#
#530
1#
b01000101 )
b01111000 *
b011110111 +
b011000100 ,
b11110111 -
#531
0#
#532
1#
b01001101 )
b01110110 *
b011110110 +
b011000011 ,
b11110110 -
#533
0#
#534
1#
b01010101 )
b01110100 *
b011110101 +
b011000010 ,
b11110101 -
#535
0#
#536
1#
b01011101 )
b01110001 *
b011110100 +
b011000001 ,
b11110100 -
#537
0#
#538
1#
b01100111 )
b01101101 *
b011110011 +
b011000000 ,
b11110011 -
#539
0#
#540
1#
b01101010 )
b01101001 *
b011110010 +
b010111111 ,
b11110010 -
#541
0#
#542
1#
b01101001 )
b01101000 *
b011110001 +
b010111110 ,
b11110001 -
#543
0#
#544
1#
b01101011 *
b011110000 +
b010111101 ,
b11110000 -
#545
0#
#546
1#
b01101000 )
b011101111 +
b010111100 ,
b11101111 -
#547
0#
#548
1#
b01100001 )
b01101110 *
b011101110 +
b010111011 ,
b11101110 -
#549
0#
#550
1#
b01101100 *
b011101101 +
b010111010 ,
b11101101 -
#551
0#
#552
1#
b01100100 )
b01100111 *
b011101100 +
b010111001 ,
b11101100 -
#553
0#
#554
1#
b01100011 )
b01100010 *
b011101011 +
b010111000 ,
b11101011 -
#555
0#
#556
1#
b01100110 )
b01100001 *
b011101010 +
b010110111 ,
b11101010 -
#557
0#
#558
1#
b01101010 )
b01100010 *
b011101001 +
b010110110 ,
b11101001 -
#559
0#
#560
1#
b01101101 )
b01100011 *
b011101000 +
b010110101 ,
b11101000 -
#561
0#
#562
1#
b01101111 )
b01100000 *
b011100111 +
b010110100 ,
b11100111 -
#563
0#
#564
1#
b01101110 )
b011100110 +
b010110011 ,
b11100110 -
#565
0#
#566
1#
b01110001 )
b01100100 *
b011100101 +
b010110010 ,
b11100101 -
#567
0#
#568
1#
b01110000 )
b01100110 *
b011100100 +
b010110001 ,
b11100100 -
#569
0#
#570
1#
b01101010 )
b01101100 *
b011100011 +
b010110000 ,
b11100011 -
#571
0#
#572
1#
b01101101 )
b01101101 *
b011100010 +
b010101111 ,
b11100010 -
#573
0#
#574
1#
b01101100 *
b011100001 +
b010101110 ,
b11100001 -
#575
0#
#576
1#
b01101011 )
b01101111 *
b011100000 +
b010101101 ,
b11100000 -
#577
0#
#578
1#
b01100111 )
b01110001 *
b011011111 +
b010101100 ,
b11011111 -
#579
0#
#580
1#
b011011110 +
b010101011 ,
b11011110 -
#581
0#
#582
1#
b01101010 )
b01101100 *
b011011101 +
b010101010 ,
b11011101 -
#583
0#
#584
1#
b01101100 )
b01100110 *
b011011100 +
b010101001 ,
b11011100 -
#585
0#
#586
1#
b01110100 )
b01100101 *
b011011011 +
b010101000 ,
b11011011 -
#587
0#
#588
1#
b01110101 )
b011011010 +
b010100111 ,
b11011010 -
#589
0#
#590
1#
b01100100 *
b011011001 +
b010100110 ,
b11011001 -
#591
0#
#592
1#
b01110110 )
b01101010 *
b011011000 +
b010100101 ,
b11011000 -
#593
0#
#594
1#
b01110010 )
b01100110 *
b011010111 +
b010100100 ,
b11010111 -
#595
0#
#596
1#
b01110001 )
b01100111 *
b011010110 +
b010100011 ,
b11010110 -
#597
0#
#598
1#
b01101001 )
b01101110 *
b011010101 +
b010100010 ,
b11010101 -
#599
0#
#600
1#
b01100101 )
b01101100 *
b011010100 +
b010100001 ,
b11010100 -
#601
0#
#602
1#
b01101101 *
b011010011 +
b010100000 ,
b11010011 -
#603
0#
#604
1#
b01100001 )
b01101011 *
b011010010 +
b010011111 ,
b11010010 -
#605
0#
#606
1#
b01100100 *
b011010001 +
b010011110 ,
b11010001 -
#607
0#
#608
1#
b01100110 )
b011010000 +
b010011101 ,
b11010000 -
#609
0#
#610
1#
b01100011 *
b011001111 +
b010011100 ,
b11001111 -
#611
0#
#612
1#
b01100111 )
b01100100 *
b011001110 +
b010011011 ,
b11001110 -
#613
0#
#614
1#
b01101100 )
b01101011 *
b011001101 +
b010011010 ,
b11001101 -
#615
0#
#616
1#
b01110010 )
b01101001 *
b011001100 +
b010011001 ,
b11001100 -
#617
0#
#618
1#
b01110101 )
b01101101 *
b011001011 +
b010011000 ,
b11001011 -
#619
0#
#620
1#
b01110111 )
b01101111 *
b011001010 +
b010010111 ,
b11001010 -
#621
0#
#622
1#
b01110110 )
b01101101 *
b011001001 +
b010010110 ,
b11001001 -
#623
0#
#624
1#
b01110101 )
b01101100 *
b011001000 +
b010010101 ,
b11001000 -
#625
0#
#626
1#
b01101110 )
b01101000 *
b011000111 +
b010010100 ,
b11000111 -
#627
0#
#628
1#
b01101100 )
b01101010 *
b011000110 +
b010010011 ,
b11000110 -
#629
0#
#630
1#
b01101110 )
b01101110 *
b011000101 +
b010010010 ,
b11000101 -
#631
0#
#632
1#
b011000100 +
b010010001 ,
b11000100 -
#633
0#
#634
1#
b01101101 *
b011000011 +
b010010000 ,
b11000011 -
#635
0#
#636
1#
b01101100 )
b01101110 *
b011000010 +
b010001111 ,
b11000010 -
#637
0#
